pyprland/__init__.py
pyprland/adapters/__init__.py
pyprland/adapters/backend.py
pyprland/adapters/colors.py
pyprland/adapters/fallback.py
pyprland/adapters/hyprland.py
pyprland/adapters/menus.py
pyprland/adapters/niri.py
pyprland/adapters/proxy.py
pyprland/adapters/units.py
pyprland/adapters/wayland.py
pyprland/adapters/xorg.py
pyprland/aioops.py
pyprland/ansi.py
pyprland/client.py
pyprland/command.py
pyprland/command_registry.py
pyprland/common.py
pyprland/completions.py
pyprland/config.py
pyprland/config_loader.py
pyprland/constants.py
pyprland/debug.py
pyprland/help.py
pyprland/httpclient.py
pyprland/ipc.py
pyprland/ipc_paths.py
pyprland/logging_setup.py
pyprland/manager.py
pyprland/models.py
pyprland/plugins/__init__.py
pyprland/plugins/experimental.py
pyprland/plugins/expose.py
pyprland/plugins/fcitx5_switcher.py
pyprland/plugins/fetch_client_menu.py
pyprland/plugins/interface.py
pyprland/plugins/layout_center.py
pyprland/plugins/lost_windows.py
pyprland/plugins/magnify.py
pyprland/plugins/menubar.py
pyprland/plugins/mixins.py
pyprland/plugins/monitors/__init__.py
pyprland/plugins/monitors/commands.py
pyprland/plugins/monitors/layout.py
pyprland/plugins/monitors/resolution.py
pyprland/plugins/monitors/schema.py
pyprland/plugins/protocols.py
pyprland/plugins/pyprland/__init__.py
pyprland/plugins/pyprland/hyprland_core.py
pyprland/plugins/pyprland/niri_core.py
pyprland/plugins/pyprland/schema.py
pyprland/plugins/scratchpads/__init__.py
pyprland/plugins/scratchpads/animations.py
pyprland/plugins/scratchpads/common.py
pyprland/plugins/scratchpads/events.py
pyprland/plugins/scratchpads/helpers.py
pyprland/plugins/scratchpads/lifecycle.py
pyprland/plugins/scratchpads/lookup.py
pyprland/plugins/scratchpads/objects.py
pyprland/plugins/scratchpads/schema.py
pyprland/plugins/scratchpads/transitions.py
pyprland/plugins/scratchpads/windowruleset.py
pyprland/plugins/shift_monitors.py
pyprland/plugins/shortcuts_menu.py
pyprland/plugins/system_notifier.py
pyprland-3.0.0.dist-info/METADATA
pyprland-3.0.0.dist-info/WHEEL
pyprland-3.0.0.dist-info/entry_points.txt
pyprland-3.0.0.dist-info/licenses/LICENSE
pyprland-3.0.0.dist-info/RECORD
