Metadata-Version: 2.4
Name: pyprland
Version: 3.0.0
Summary: A companion for your desktop UX
License-Expression: MIT
License-File: LICENSE
Author: Fabien Devaux
Author-email: fdev31 <fdev31@gmail.com>
Requires-Python: >=3.11
Classifier: Programming Language :: Python :: 3
Classifier: Programming Language :: Python :: 3.11
Classifier: Programming Language :: Python :: 3.12
Classifier: Programming Language :: Python :: 3.13
Classifier: Programming Language :: Python :: 3.14
Requires-Dist: aiofiles
Requires-Dist: aiohttp
Requires-Dist: pillow
Requires-Dist: questionary[quickstart]
